odoo9_addon_mrp_bom_component_menu-9.0.1.0.0-py2.7-nspkg.pth
odoo9_addon_mrp_bom_component_menu-9.0.1.0.0.dist-info/DESCRIPTION.rst
odoo9_addon_mrp_bom_component_menu-9.0.1.0.0.dist-info/METADATA
odoo9_addon_mrp_bom_component_menu-9.0.1.0.0.dist-info/RECORD
odoo9_addon_mrp_bom_component_menu-9.0.1.0.0.dist-info/WHEEL
odoo9_addon_mrp_bom_component_menu-9.0.1.0.0.dist-info/metadata.json
odoo9_addon_mrp_bom_component_menu-9.0.1.0.0.dist-info/namespace_packages.txt
odoo9_addon_mrp_bom_component_menu-9.0.1.0.0.dist-info/top_level.txt
odoo_addons/mrp_bom_component_menu/README.rst
odoo_addons/mrp_bom_component_menu/__init__.py
odoo_addons/mrp_bom_component_menu/__openerp__.py
odoo_addons/mrp_bom_component_menu/static/description/icon.png
odoo_addons/mrp_bom_component_menu/views/mrp_bom_component_view.xml
